README.rst
setup.cfg
setup.py
career/__init__.py
career/admin.py
career/forms.py
career/models.py
career/urls.py
career/views.py
career.egg-info/PKG-INFO
career.egg-info/SOURCES.txt
career.egg-info/dependency_links.txt
career.egg-info/not-zip-safe
career.egg-info/requires.txt
career.egg-info/top_level.txt
career/migrations/0001_initial.py
career/migrations/__init__.py
career/templatetags/__init__.py
career/templatetags/career.py