Metadata-Version: 1.1
Name: career
Version: 0.0.1
Summary: The very basic to start some elearning activity
Home-page: https://github.com/danieltellez/career
Author: Daniel Tellez
Author-email: danieltellez@flossfriday.com
License: UNKNOWN
Platform: UNKNOWN
Classifier: Development Status :: 3 - Alpha
Classifier: Framework :: Django
Classifier: Intended Audience :: Other Audience
Classifier: License :: OSI Approved :: GNU General Public License v2 (GPLv2)
Classifier: Operating System :: OS Independent
Classifier: Programming Language :: Python
Classifier: Topic :: Education
